[
  {
    "title": "Technical",
    "values": [
      "JavaScript",
      "Python",
      "Django",
      "React",
      "Node.js",
      "HTML",
      "CSS",
      "SQL",
      "NoSQL",
      "Postgres",
      "MySQL",
      "DataDog",
      "Sentry",
      "SnowFlake",
      "mParticle"
    ]
  },
  {
    "title": "Testing & QA",
    "values": [
      "TestRail",
      "Zebrunner",
      "BrowserStack",
      "Cypress",
      "Postman",
      "API Testing",
      "Automation",
      "E2E"
    ]
  },
  {
    "title": "Project Management & DevOps",
    "values": [
      "Jira",
      "Confluence",
      "AWS",
      "Azure",
      "Jenkins",
      "GitHub Actions",
      "Slack"
    ]
  },

  {
    "title": "Soft",
    "values": ["Communication", "Leadership", "Teamwork"]
  }
]
